LICENSE.txt
MANIFEST.in
README.rst
demo_ezprettyjson.ipynb
setup.cfg
setup.py
ezprettyjson/__init__.py
ezprettyjson/prettyjson.py
ezprettyjson.egg-info/PKG-INFO
ezprettyjson.egg-info/SOURCES.txt
ezprettyjson.egg-info/dependency_links.txt
ezprettyjson.egg-info/top_level.txt